odoo/addons/product_pricelist_margin/README.rst
odoo/addons/product_pricelist_margin/__init__.py
odoo/addons/product_pricelist_margin/__manifest__.py
odoo/addons/product_pricelist_margin/demo/product_pricelist.xml
odoo/addons/product_pricelist_margin/demo/product_product.xml
odoo/addons/product_pricelist_margin/demo/res_groups.xml
odoo/addons/product_pricelist_margin/i18n/fr.po
odoo/addons/product_pricelist_margin/i18n/product_pricelist_margin.pot
odoo/addons/product_pricelist_margin/models/__init__.py
odoo/addons/product_pricelist_margin/models/product_product.py
odoo/addons/product_pricelist_margin/models/product_template.py
odoo/addons/product_pricelist_margin/readme/CONTRIBUTORS.rst
odoo/addons/product_pricelist_margin/readme/DESCRIPTION.rst
odoo/addons/product_pricelist_margin/readme/INSTALL.rst
odoo/addons/product_pricelist_margin/readme/USAGE.rst
odoo/addons/product_pricelist_margin/static/description/icon.png
odoo/addons/product_pricelist_margin/static/description/index.html
odoo/addons/product_pricelist_margin/static/description/product_template_form.png
odoo/addons/product_pricelist_margin/static/description/with_module_web_tree_dynamic_colored_field.png
odoo/addons/product_pricelist_margin/static/description/wizard_preview_pricelist_margin_form.png
odoo/addons/product_pricelist_margin/tests/__init__.py
odoo/addons/product_pricelist_margin/tests/test_module.py
odoo/addons/product_pricelist_margin/views/view_product_template.xml
odoo/addons/product_pricelist_margin/wizards/__init__.py
odoo/addons/product_pricelist_margin/wizards/wizard_preview_pricelist_margin.py
odoo/addons/product_pricelist_margin/wizards/wizard_preview_pricelist_margin.xml
odoo/addons/product_pricelist_margin/wizards/wizard_preview_pricelist_margin_line.py
odoo12_addon_product_pricelist_margin-12.0.1.0.0.99.dev6.dist-info/METADATA
odoo12_addon_product_pricelist_margin-12.0.1.0.0.99.dev6.dist-info/WHEEL
odoo12_addon_product_pricelist_margin-12.0.1.0.0.99.dev6.dist-info/top_level.txt
odoo12_addon_product_pricelist_margin-12.0.1.0.0.99.dev6.dist-info/RECORD
